pysettings/__init__.py
pysettings/base.py
pysettings/exceptions.py
pysettings/options.py
pysettings/validators.py
pysettings/test/__init__.py
pysettings/test/wrappers.py
pysettings_validator-0.4.0.dist-info/LICENSE
pysettings_validator-0.4.0.dist-info/METADATA
pysettings_validator-0.4.0.dist-info/WHEEL
pysettings_validator-0.4.0.dist-info/top_level.txt
pysettings_validator-0.4.0.dist-info/RECORD
