Metadata-Version: 2.1
Name: pysettings-validator
Version: 0.4.0
Summary: Python package to store your application settings. Validators are built-in!
Home-page: https://github.com/palazzem/pysettings
Author: Emanuele Palazzetti
Author-email: emanuele.palazzetti@gmail.com
License: BSD 3-Clause
Classifier: Development Status :: 4 - Beta
Classifier: Intended Audience :: Developers
Classifier: License :: OSI Approved :: BSD License
Classifier: Programming Language :: Python
Classifier: Programming Language :: Python :: 3
Classifier: Programming Language :: Python :: 3.7
Classifier: Programming Language :: Python :: 3.8
Classifier: Programming Language :: Python :: 3.9
Classifier: Programming Language :: Python :: 3.10
Requires-Python: >=3.7.0
License-File: LICENSE
